{
	"id": "b1fb7e43-c3da-4580-b01d-27984be28db1",
	"name": "Tyk - Staging",
	"values": [
		{
			"key": "CatalogSlug",
			"value": "catalog-staging",
			"enabled": true
		},
		{
			"key": "UserSlug",
			"value": "user-management-staging",
			"enabled": true
		},
		{
			"key": "OrderSlug",
			"value": "order-management-staging",
			"enabled": true
		},
		{
			"key": "AdressSlug",
			"value": "address-management-staging",
			"type": "default",
			"enabled": true
		},
		{
			"key": "ApiKey",
			"value": "eyJvcmciOiI2MGEyMTNjYTcyMTMzZjAwMDFlOWZlODMiLCJpZCI6ImRmNDE1ZGMxNTJiYjQ5NDJiMjVmOGU1NTFhYTE0ZTA4IiwiaCI6Im11cm11cjEyOCJ9",
			"enabled": true
		},
		{
			"key": "ImagesSlug",
			"value": "api-images-staging",
			"enabled": true
		},
		{
			"key": "UserSignInPassword",
			"value": "Please1!",
			"enabled": false
		},
		{
			"key": "ShopEmail",
			"value": "testvendeur2106@mvms.fr",
			"type": "default",
			"enabled": true
		},
		{
			"key": "ShopId",
			"value": "7143",
			"enabled": true
		},
		{
			"key": "ShopPassword",
			"value": "Ben@194561",
			"type": "default",
			"enabled": true
		},
		{
			"key": "BaseUrl",
			"value": "https://stingy-advice-gw.aws-euc1.cloud-ara.tyk.io",
			"enabled": true
		},
		{
			"key": "AdminEmail",
			"value": "admin@e-city.fr",
			"type": "default",
			"enabled": false
		},
		{
			"key": "AdminPassword",
			"value": "2017%Ecity",
			"type": "default",
			"enabled": false
		},
		{
			"key": "UserEmail",
			"value": "testclient0308@mavms.fr",
			"type": "default",
			"enabled": true
		},
		{
			"key": "UserPassword",
			"value": "Ben@194561",
			"type": "default",
			"enabled": true
		},
		{
			"key": "UserId",
			"value": "17149",
			"type": "default",
			"enabled": true
		},
		{
			"key": "CityzenEmail",
			"value": "cityzen1664889747250@mvms.fr",
			"type": "default",
			"enabled": true
		},
		{
			"key": "CityzenPassword",
			"value": "Ben@194561",
			"type": "default",
			"enabled": true
		},
		{
			"key": "CityzenId",
			"value": "9897",
			"type": "default",
			"enabled": true
		},
		{
			"key": "CityzenImageId",
			"value": "166719",
			"type": "default",
			"enabled": true
		},
		{
			"key": "ProductId",
			"value": "82286",
			"type": "default",
			"enabled": false
		},
		{
			"key": "email",
			"value": "",
			"type": "any",
			"enabled": true
		},
		{
			"key": "CustomerEmail",
			"value": "customer1664888960936@mvms.fr",
			"type": "any",
			"enabled": true
		},
		{
			"key": "token",
			"value": "",
			"type": "any",
			"enabled": true
		},
		{
			"key": "NameProduct",
			"value": "piment",
			"type": "any",
			"enabled": true
		},
		{
			"key": "StatSlug",
			"value": "statistics-staging",
			"type": "any",
			"enabled": true
		},
		{
			"key": "CategoryId",
			"value": "2903",
			"type": "default",
			"enabled": true
		},
		{
			"key": "CreateNotification",
			"value": "",
			"type": "any",
			"enabled": true
		},
		{
			"key": "ProductId",
			"value": "84299",
			"type": "any",
			"enabled": true
		},
		{
			"key": "XclientId",
			"value": "eyJhbGciOiJIUzI1NiJ9.eyJpZCI6MTg0NjcsInVzZXJfdHlwZSI6ImN1c3RvbWVyIiwiZXhwIjoxNjY0NDM5NzgzfQ.y-j6yVbja8Qn7dGKEmXrM8kk6Ro38t8FqPz9ezZMWY8",
			"type": "any",
			"enabled": true
		},
		{
			"key": "userId",
			"value": "",
			"type": "any",
			"enabled": true
		},
		{
			"key": "VariantId",
			"value": "",
			"type": "any",
			"enabled": true
		},
		{
			"key": "idNotifications",
			"value": "529",
			"type": "any",
			"enabled": true
		},
		{
			"key": "idimage",
			"value": "",
			"type": "any",
			"enabled": true
		},
		{
			"key": "VendeurEmail",
			"value": "",
			"type": "any",
			"enabled": true
		},
		{
			"key": "TokenShop",
			"value": "",
			"type": "any",
			"enabled": true
		},
		{
			"key": "Shoptoken",
			"value": "",
			"type": "any",
			"enabled": true
		},
		{
			"key": "cityzenId",
			"value": "",
			"type": "any",
			"enabled": true
		},
		{
			"key": "AdminToken",
			"value": "",
			"type": "any",
			"enabled": true
		},
		{
			"key": "ShopToken",
			"value": "",
			"type": "any",
			"enabled": true
		},
		{
			"key": "UserShopId",
			"value": "15910",
			"type": "default",
			"enabled": true
		},
		{
			"key": "ShopName",
			"value": "",
			"type": "any",
			"enabled": true
		},
		{
			"key": "CreateShoptoken",
			"value": "",
			"type": "any",
			"enabled": true
		},
		{
			"key": "CreateShopEmail",
			"value": "",
			"type": "any",
			"enabled": true
		},
		{
			"key": "CreateShopId",
			"value": "",
			"type": "any",
			"enabled": true
		},
		{
			"key": "CreateProductId",
			"value": "",
			"type": "any",
			"enabled": true
		},
		{
			"key": "DimancheId",
			"value": "",
			"type": "any",
			"enabled": true
		},
		{
			"key": "SelectionId",
			"value": "278",
			"type": "any",
			"enabled": true
		},
		{
			"key": "CityzenToken",
			"value": "",
			"type": "any",
			"enabled": true
		},
		{
			"key": "NameProductSubmitted",
			"value": "",
			"type": "any",
			"enabled": true
		},
		{
			"key": "CreateCategoryId",
			"value": "",
			"type": "any",
			"enabled": true
		},
		{
			"key": "CreateVariantId",
			"value": "",
			"type": "any",
			"enabled": true
		},
		{
			"key": "VariantUpdate",
			"value": "",
			"type": "any",
			"enabled": true
		},
		{
			"key": "ShopSchedulesToken",
			"value": "",
			"type": "any",
			"enabled": true
		},
		{
			"key": "ThirdPart GLOBAL API PREPRODUCTION",
			"value": "eyJvcmciOiI2MGEyMTNjYTcyMTMzZjAwMDFlOWZlODMiLCJpZCI6ImNmYjdjYzE5ZmEzZDRjMTViM2FhZWZiMjk0ZDE1YjlkIiwiaCI6Im11cm11cjEyOCJ9",
			"type": "default",
			"enabled": true
		},
		{
			"key": "SelectionToken",
			"value": "",
			"type": "any",
			"enabled": true
		},
		{
			"key": "SelectionName",
			"value": "",
			"type": "any",
			"enabled": true
		},
		{
			"key": "SelectionImgId",
			"value": "",
			"type": "any",
			"enabled": true
		},
		{
			"key": "ShopsSlug",
			"value": "shops-staging",
			"type": "default",
			"enabled": true
		},
		{
			"key": "CartSlug",
			"value": "cart-staging",
			"type": "default",
			"enabled": true
		},
		{
			"key": "CartProductId",
			"value": "",
			"type": "any",
			"enabled": true
		},
		{
			"key": "CartVariantId",
			"value": "",
			"type": "any",
			"enabled": true
		},
		{
			"key": "CartId",
			"value": "",
			"type": "any",
			"enabled": true
		},
		{
			"key": "CartToken",
			"value": "",
			"type": "any",
			"enabled": true
		},
		{
			"key": "CartVariantId1",
			"value": "",
			"type": "any",
			"enabled": true
		},
		{
			"key": "cartEntriesId",
			"value": "",
			"type": "any",
			"enabled": false
		},
		{
			"key": "CartEntriesId",
			"value": "",
			"type": "any",
			"enabled": true
		},
		{
			"key": "CustomerCartId",
			"value": "",
			"type": "any",
			"enabled": true
		},
		{
			"key": 195217,
			"value": "",
			"type": "any",
			"enabled": true
		},
		{
			"key": "CustomerPassword",
			"value": "Ben@194561",
			"type": "any",
			"enabled": true
		},
		{
			"key": "SearchAdress",
			"value": "",
			"type": "any",
			"enabled": true
		},
		{
			"key": "localityId",
			"value": "",
			"type": "any",
			"enabled": true
		},
		{
			"key": "streetId",
			"value": "",
			"type": "any",
			"enabled": true
		},
		{
			"key": "streetNumberId",
			"value": "",
			"type": "any",
			"enabled": true
		},
		{
			"key": "streetNumber",
			"value": "",
			"type": "any",
			"enabled": true
		},
		{
			"key": "latitude",
			"value": "",
			"type": "any",
			"enabled": true
		},
		{
			"key": "longitude",
			"value": "",
			"type": "any",
			"enabled": true
		},
		{
			"key": "authToken",
			"value": "",
			"type": "any",
			"enabled": true
		},
		{
			"key": "productName",
			"value": "",
			"type": "any",
			"enabled": true
		},
		{
			"key": "productId",
			"value": "",
			"type": "any",
			"enabled": true
		},
		{
			"key": "variantId",
			"value": "",
			"type": "any",
			"enabled": true
		},
		{
			"key": "Cityzentoken",
			"value": "",
			"type": "any",
			"enabled": true
		},
		{
			"key": "CustomerToken",
			"value": "",
			"type": "any",
			"enabled": true
		},
		{
			"key": "CustomerId",
			"value": "",
			"type": "any",
			"enabled": true
		},
		{
			"key": "NotificationProduct",
			"value": "",
			"type": "any",
			"enabled": true
		},
		{
			"key": "NotificationId",
			"value": "",
			"type": "any",
			"enabled": true
		},
		{
			"key": "CreateProductCityzen",
			"value": "",
			"type": "any",
			"enabled": true
		},
		{
			"key": "AddresId",
			"value": "",
			"type": "any",
			"enabled": true
		},
		{
			"key": "TerritoryId",
			"value": "321",
			"type": "default",
			"enabled": true
		},
		{
			"key": "MartName",
			"value": "",
			"type": "any",
			"enabled": true
		},
		{
			"key": "MartEmail",
			"value": "",
			"type": "any",
			"enabled": true
		},
		{
			"key": "martId",
			"value": "",
			"type": "any",
			"enabled": true
		},
		{
			"key": "ReviewId",
			"value": "",
			"type": "any",
			"enabled": true
		}
	],
	"_postman_variable_scope": "environment",
	"_postman_exported_at": "2022-11-09T13:52:18.558Z",
	"_postman_exported_using": "Postman/10.2.0-221107-1307"
}